{
    "items": [
              {
              "id": "0001",
              "event-type": "Concert",
              "name": "Lorde In Consert",
              "location": "Ashford",
              "description": "A concert is a live performance of music before an audience. The performance may be by a single musician, sometimes then called a recital, or by a musical ensemble, such as an orchestra, a choir, or a musical band. Concerts are held in a wide variety and size of settings, from private houses and small nightclubs, dedicated concert halls, entertainment centres and parks to large multipurpose buildings, and even sports stadiums.",
              "date": "2014-04-21T18:25:43-05:00",
              "categories": [
                             "Groups",
                             "kids frindly"
                             ],
              "coordinate": {
              "latitude": 51.431549,
              "longitude": -0.474782
              },
              "event-images": [
                               "https://api-content.dropbox.com/1/files/dropbox//EventPilot/Brighton_1.PNG”,
                               "https://api-content.dropbox.com/1/files/dropbox//EventPilot/Brighton_2.PNG”
                               ],
              "thumbnail": "https://api-content.dropbox.com/1/files/dropbox//EventPilot/Bluehound.gif"
              },
              {
              "id": "0002",
              "event-type": "Music",
              "name": "Live Music for  kids",
              "location": "London",
              "description": "Music is an art form whose medium is sound and silence. Its common elements are pitch (which governs melody and harmony), rhythm.",
              "date": "2014-05-21T18:25:43-05:00",
              "price": "$60.00",
              "categories": [
                             "Groups",
                             "kids frindly"
                             ],
              "coordinate": {
              "latitude": 51.431549,
              "longitude": -0.474782
              },
              "event-images": [
                               "https://api-content.dropbox.com/1/files/dropbox//EventPilot/Brighton_3.PNG”,
                               "https://api-content.dropbox.com/1/files/dropbox//EventPilot/Brighton_4.PNG”
                               ],
              "thumbnail": "images/thumbnails/0001.jpg"
              }
              ]
}